azure_strg_utils/__init__.py
azure_strg_utils/azure_strg_utils.py
azure_strg_utils/exceptions.py
azure_strg_utils/utils.py
azure_strg_utils/version.py
azure_strg_utils-0.2.2.dist-info/LICENSE.txt
azure_strg_utils-0.2.2.dist-info/METADATA
azure_strg_utils-0.2.2.dist-info/WHEEL
azure_strg_utils-0.2.2.dist-info/top_level.txt
azure_strg_utils-0.2.2.dist-info/RECORD
