Metadata-Version: 2.1
Name: azure-strg-utils
Version: 0.2.2
Summary: The package facilitates interaction with Azure storage accounts, enabling the execution of a wide range of operations on these accounts.
Home-page: https://github.com/1997vijay/AzureBlobUtils.git
Author: Vijay Kumar
Author-email: vijay.kumar.1997@outlook.com
License: MIT
Keywords: azure,storage,blob,container
Classifier: Development Status :: 4 - Beta
Classifier: Intended Audience :: Developers
Classifier: Topic :: Software Development
Classifier: License :: OSI Approved :: MIT License
Classifier: Programming Language :: Python
Classifier: Programming Language :: Python :: 3.8
Classifier: Programming Language :: Python :: 3.9
Classifier: Programming Language :: Python :: 3.10
Classifier: Programming Language :: Python :: 3.11
Requires-Python: >=3.9
License-File: LICENSE.txt
Requires-Dist: azure-storage-blob >=12.0.0
Requires-Dist: pandas
